shopcloud_streams/__init__.py
shopcloud_streams-1.4.0.dist-info/LICENSE
shopcloud_streams-1.4.0.dist-info/METADATA
shopcloud_streams-1.4.0.dist-info/WHEEL
shopcloud_streams-1.4.0.dist-info/top_level.txt
shopcloud_streams-1.4.0.dist-info/RECORD
