Metadata-Version: 2.1
Name: shopcloud-streams
Version: 1.4.0
Summary: CLI Tool for Shopcloud Streams
Home-page: https://github.com/Talk-Point/shopcloud-streams-cli
Author: Konstantin Stoldt
Author-email: konstantin.stoldt@talk-point.de
License: MIT
Keywords: CLI
License-File: LICENSE
Requires-Dist: requests
Requires-Dist: shopcloud-secrethub
